{
    "total": 123,
    "data": [
        {
            "username": "ASDAS",
            "password": "123"
        },
        {
            "username": "ASDAS",
            "password": "123"
        },
        {
            "username": "ASDAS",
            "password": "123"
        },
        {
            "username": "ASDAS",
            "password": "123123412213123"
        },
        {
            "username": "ASDAS",
            "password": "123"
        },
        {
            "username": "洪江",
            "password": "asd"
        }
    ]
}